{
  "year": 2023,
  "round": 11,
  "country": "Hungary",
  "location": "Budapest",
  "officialName": "FORMULA 1 QATAR AIRWAYS HUNGARIAN GRAND PRIX 2023",
  "eventName": "Hungarian Grand Prix",
  "eventDate": "2023-07-23 00:00:00",
  "eventFormat": "conventional",
  "sessions": {
    "fp1": {
      "name": "Practice 1",
      "date": "2023-07-21 13:30:00+02:00"
    },
    "fp2": {
      "name": "Practice 2",
      "date": "2023-07-21 17:00:00+02:00"
    },
    "fp3": {
      "name": "Practice 3",
      "date": "2023-07-22 12:30:00+02:00"
    },
    "qualifying": {
      "name": "Qualifying",
      "date": "2023-07-22 16:00:00+02:00"
    },
    "race": {
      "name": "Race",
      "date": "2023-07-23 15:00:00+02:00"
    }
  }
}